{
  "lastUpdated": "2020-12-25T20:55:02.818Z",
  "seriesId": "2070",
  "title": "CYCLE AROUND JAPAN  Highlights",
  "episodes": [
    {
      "airingId": "030",
      "content": "Our ironman cyclist Michael sets off from Osaka. Leaving the giant city, he tackles the challenge of Japan's steepest road on his way to historic Nara Prefecture, site of the capital 1,300 years ago. As he rides through this tranquil countryside, he dives into a world of myth -- from Nara's sacred forest, brilliant with the colors of fall, he travels south to a land teeming with prehistoric burial mounds. Here, where ancient rulers slept for millennia, the old wisdom still shows us how to live in harmony with nature.",
      "description": "This ride through Nara, site of Japan's ancient capital, takes us through historic locations bright with the colors of fall, a tranquil countryside brimming with the wisdom of the old days.",
      "endDate": "2020-12-24T15:00:00.000Z",
      "link": "https://mega.nz/folder/AVkw1YCT#Ile6Q_GoQjBvJSZqyQ5wgQ",
      "recordDateEnd": "2020-12-24T15:00:27.461Z",
      "recordDateStart": "2020-12-24T14:29:23.994Z",
      "seriesId": "2070",
      "sha256": "56621ec514a647234ec4f06c153ec265a1ef8e55fb7074ccf86ed6ee8275154e",
      "startDate": "2020-12-24T14:30:00.000Z",
      "subtitle": "Nara - Discovering Ancient Ways",
      "title": "CYCLE AROUND JAPAN  Highlights",
      "uploadedDate": "2020-12-24T22:41:28.471Z",
      "raw": "https://mega.nz/folder/O1EFGara#l1KWm6jfbEavcKNhdBkzFw"
    }
  ]
}