{
  "lastUpdated": "2020-12-26T16:35:02.695Z",
  "seriesId": "4031",
  "title": "GATTEN!",
  "episodes": [
    {
      "airingId": "005",
      "content": "The number one problem that seniors have with urination is nocturia --frequent nighttime urination. Getting up to use the toilet several times a night can disrupt your sleep and even lead to depression or serious injury. Many people think nocturia is an inevitable part of getting old, but we now know that most cases have a specific cause: the water you consume during the day is being stored up in a certain part of your body ... and it's not your bladder. However, with some easy methods anyone can do, you can reduce your nocturia!",
      "description": "You might think that frequent nighttime urination is an inevitable part of getting older, but we know now it usually has a specific cause that some easy methods can help to prevent!",
      "endDate": "2020-12-05T04:55:00.000Z",
      "link": "https://mega.nz/folder/Mw02gYTY#Q-I1RwrSqifHHpSVN-84rA",
      "recordDateEnd": "2020-12-05T04:55:25.273Z",
      "recordDateStart": "2020-12-05T04:09:20.122Z",
      "seriesId": "4031",
      "sha256": "f096d43f8f4809fc45f09ee61f6fed3444ae1cb6b1c9bb12a1fa5b05270d0f00",
      "startDate": "2020-12-05T04:10:00.000Z",
      "subtitle": "Ending Nighttime Urination",
      "title": "GATTEN!",
      "uploadedDate": "2020-12-25T05:15:45.953Z"
    }
  ]
}