{
  "lastUpdated": "2020-12-26T12:50:03.058Z",
  "seriesId": "3004",
  "title": "Drainspotters #4 Morning Market",
  "episodes": [
    {
      "airingId": "429",
      "content": "",
      "description": "Japan's artistic manhole covers tell the tale of a different town or region of the country. The morning market in Wajima is home to over a thousand years of tradition.",
      "endDate": "2020-12-20T00:00:00.000Z",
      "link": "https://mega.nz/folder/nItz1aoY#NfsaHZkfeD6YyS2wzFNa1w",
      "recordDateEnd": "2020-12-20T00:01:13.325Z",
      "recordDateStart": "2020-12-19T23:56:23.004Z",
      "seriesId": "3004",
      "sha256": "2adb985ceff3316a62b1dce79654756fd8ca20eccbcbf0c837b8006e3dc76cd6",
      "startDate": "2020-12-19T23:57:00.000Z",
      "subtitle": "",
      "title": "Drainspotters #4 Morning Market",
      "uploadedDate": "2020-12-25T18:10:05.431Z"
    }
  ]
}