{
  "lastUpdated": "2020-12-25T18:20:03.288Z",
  "seriesId": "2075",
  "title": "Doki Doki! NHK WORLD-JAPAN",
  "episodes": [
    {
      "airingId": "073",
      "content": "",
      "description": "This time we introduce NHK WORLD-JAPAN's new program \"The Signs.\" This episode shows various roles of \"avatar\" in this \"COVID-19 period,\" such as working in the office or attending the events.",
      "endDate": "2020-12-06T11:55:00.000Z",
      "link": "https://mega.nz/folder/Ud8TkACC#nhpO351avxT7gNG4ODfl2Q",
      "recordDateEnd": "2020-12-06T11:55:23.612Z",
      "recordDateStart": "2020-12-06T11:49:22.937Z",
      "seriesId": "2075",
      "sha256": "53a7411ecd2f6e536a7cb7ba8b0209c30b21c82b5e52ffbf24034a6640218efd",
      "startDate": "2020-12-06T11:50:00.000Z",
      "subtitle": "",
      "title": "Doki Doki! NHK WORLD-JAPAN",
      "uploadedDate": "2020-12-25T18:16:20.097Z"
    }
  ]
}