{
  "lastUpdated": "2021-01-19T05:30:04.097Z",
  "seriesId": "6109",
  "title": "Winter Joy",
  "episodes": [
    {
      "airingId": "005",
      "content": "",
      "description": "Winter brings joy to Japan. Enjoy the beautiful landscape of Japan and enjoy the wonders of winter. #5: Enjoy the famous landscape of sheer cliffs and the region's ultimate winter delicacies.",
      "endDate": "2021-01-11T01:30:00.000Z",
      "link": "https://mega.nz/folder/QU9gkBBQ#NlhkLekNCAKxt4ThWjrvSQ",
      "recordDateEnd": "2021-01-11T01:30:24.927Z",
      "recordDateStart": "2021-01-11T01:19:23.025Z",
      "seriesId": "6109",
      "sha256": "ea7da35e8d9a2d024ff40d9cdbfa2b6ee4bbe53c6bdfa982214289f2f19a3afb",
      "startDate": "2021-01-11T01:20:00.000Z",
      "subtitle": "",
      "title": "Winter Joy",
      "uploadedDate": "2021-01-13T07:08:52.367Z",
      "raw": "https://mega.nz/folder/7o5mTZRY#rSG4DMA4c4PUoUbgkdBcOg"
    }
  ]
}