{
  "lastUpdated": "2021-04-14T16:15:04.875Z",
  "seriesId": "7000",
  "title": "Saving Pristine Shores for Future Generations",
  "episodes": [
    {
      "airingId": "469",
      "content": "",
      "description": "for Future Generations: Introduces the efforts of the local residents in coastal areas along the Sea of Japan striving to save their pristine shores from marine litter.",
      "endDate": "2021-02-10T02:00:00.000Z",
      "link": "https://mega.nz/folder/U50wFJ7J#EgYkf_qUHS28amcHuf_9xA",
      "recordDateEnd": "2021-02-10T02:00:30.343Z",
      "recordDateStart": "2021-02-10T01:29:20.099Z",
      "seriesId": "7000",
      "sha256": "dc07bca27ccbdc046a6fb5beb25f4f1b74ff3ce675902e797c0c4019f57c23b9",
      "startDate": "2021-02-10T01:30:00.000Z",
      "subtitle": "",
      "title": "Saving Pristine Shores for Future Generations",
      "uploadedDate": "2021-02-15T15:52:32.030Z",
      "raw": "https://mega.nz/folder/0AIyXTZK#9n2q7GlMkRtJZqDS8_B02g"
    }
  ]
}